easydarkfigs/__init__.py
easydarkfigs/figuremagic.py
easydarkfigs/mplstyles/easy-dark.mplstyle
easydarkfigs/mplstyles/easy-light.mplstyle
easydarkfigs-0.11.dist-info/LICENSE
easydarkfigs-0.11.dist-info/METADATA
easydarkfigs-0.11.dist-info/WHEEL
easydarkfigs-0.11.dist-info/top_level.txt
easydarkfigs-0.11.dist-info/RECORD
