Metadata-Version: 2.1
Name: easydarkfigs
Version: 0.11
Summary: iPython Magic for Easy Dark/Light Figures
Home-page: https://github.com/bacook17/easydarkfigs/
Author: Ben Cook
Author-email: bacook17@gmail.com
License: LICENSE
Keywords: matplotlib,dark figures
Platform: UNKNOWN
Classifier: Intended Audience :: Science/Research
Classifier: Programming Language :: Python
Classifier: Topic :: Software Development :: Libraries :: Python Modules
Classifier: Topic :: Scientific/Engineering :: Visualization
Requires-Dist: matplotlib
Requires-Dist: IPython
